httplens/__init__.py
httplens/abc.py
httplens/errors/__init__.py
httplens/ext/__init__.py
httplens/ext/decorators.py
httplens/interactions/__init__.py
httplens/interactions/client.py
httplens/utils/__init__.py
httplens/utils/timers.py
httplens-0.0.1.dist-info/METADATA
httplens-0.0.1.dist-info/WHEEL
httplens-0.0.1.dist-info/top_level.txt
httplens-0.0.1.dist-info/RECORD
