Metadata-Version: 2.1
Name: httplens
Version: 0.0.1
Summary: A Collection of http debugging and testing tools
Home-page: UNKNOWN
Author: quiktea
Author-email: wishymovies@gmail.com
License: UNKNOWN
Keywords: python,http,debug,testing
Platform: UNKNOWN
Classifier: Development Status :: 1 - Planning
Classifier: Intended Audience :: Developers
Classifier: Programming Language :: Python :: 3
Classifier: Operating System :: Unix
Classifier: Operating System :: MacOS :: MacOS X
Classifier: Operating System :: Microsoft :: Windows
Requires-Dist: aiohttp
